cdk_bar/__init__.py
cdk_bar/py.typed
cdk_bar/_jsii/__init__.py
cdk_bar/_jsii/cdk-bar@0.1.22.jsii.tgz
cdk_bar-0.1.22.dist-info/METADATA
cdk_bar-0.1.22.dist-info/WHEEL
cdk_bar-0.1.22.dist-info/top_level.txt
cdk_bar-0.1.22.dist-info/RECORD
