Metadata-Version: 2.1
Name: cdk-bar
Version: 0.1.22
Summary: cdk-bar
Home-page: https://github.com/pahud/cdk-bar.git
Author: Pahud<pahudnet@gmail.com>
License: Apache-2.0
Project-URL: Source, https://github.com/pahud/cdk-bar.git
Platform: UNKNOWN
Classifier: Intended Audience :: Developers
Classifier: Operating System :: OS Independent
Classifier: Programming Language :: JavaScript
Classifier: Programming Language :: Python :: 3 :: Only
Classifier: Programming Language :: Python :: 3.6
Classifier: Programming Language :: Python :: 3.7
Classifier: Programming Language :: Python :: 3.8
Classifier: Programming Language :: Python :: 3.9
Classifier: Typing :: Typed
Classifier: Development Status :: 5 - Production/Stable
Classifier: License :: OSI Approved
Requires-Python: >=3.6
Requires-Dist: aws-cdk.aws-ec2 (<2.0.0,>=1.73.0)
Requires-Dist: aws-cdk.aws-ecs-patterns (<2.0.0,>=1.73.0)
Requires-Dist: aws-cdk.aws-ecs (<2.0.0,>=1.73.0)
Requires-Dist: aws-cdk.core (<2.0.0,>=1.73.0)
Requires-Dist: constructs (<4.0.0,>=3.2.27)
Requires-Dist: jsii (<2.0.0,>=1.16.0)
Requires-Dist: publication (>=0.0.3)
